asfeslib/__init__.py
asfeslib/aviation/__init__.py
asfeslib/aviation/aero.py
asfeslib/aviation/api.py
asfeslib/aviation/data.py
asfeslib/aviation/nav.py
asfeslib/core/logger.py
asfeslib/core/sort.py
asfeslib/core/utils.py
asfeslib/databases/MongoDB.py
asfeslib/databases/MySQL.py
asfeslib/databases/PostgreSQL.py
asfeslib/databases/__init__.py
asfeslib/fastapi/usermanager/__init__.py
asfeslib/fastapi/usermanager/db_utils.py
asfeslib/fastapi/usermanager/deps.py
asfeslib/fastapi/usermanager/manager.py
asfeslib/fastapi/usermanager/router.py
asfeslib/fastapi/usermanager/schemas.py
asfeslib/fastapi/usermanager/security.py
asfeslib/fastapi/usermanager/security_password.py
asfeslib/net/http.py
asfeslib/net/mail.py
asfeslib/utils/conversions.py
asfeslib/utils/market_api.py
asfeslib/weather/__init__.py
asfeslib/weather/client.py
asfeslib/weather/models/__init__.py
asfeslib/weather/models/alerts.py
asfeslib/weather/models/astronomy.py
asfeslib/weather/models/base.py
asfeslib/weather/models/bulk.py
asfeslib/weather/models/current.py
asfeslib/weather/models/forecast.py
asfeslib/weather/models/future.py
asfeslib/weather/models/history.py
asfeslib/weather/models/ip.py
asfeslib/weather/models/marine.py
asfeslib/weather/models/responses.py
asfeslib/weather/models/search.py
asfeslib/weather/models/timezone.py
asfeslib-0.3.0.dist-info/licenses/LICENSE
asfeslib-0.3.0.dist-info/METADATA
asfeslib-0.3.0.dist-info/WHEEL
asfeslib-0.3.0.dist-info/top_level.txt
asfeslib-0.3.0.dist-info/RECORD
