Metadata-Version: 2.4
Name: asfeslib
Version: 0.3.0
Summary: Asfes hackathon core library
Author-email: Александр <proshka20081010@gmail.com>
License: MIT License
Project-URL: Homepage, https://github.com/alxprgs/asfeslib
Project-URL: Source, https://github.com/alxprgs/asfeslib
Keywords: asfes,fastapi,iot,hackathon,utils,server
Classifier: Programming Language :: Python :: 3
Classifier: Programming Language :: Python :: 3.10
Classifier: Programming Language :: Python :: 3.11
Classifier: Programming Language :: Python :: 3.12
Requires-Python: >=3.10
License-File: LICENSE
Requires-Dist: fastapi>=0.115.0
Requires-Dist: uvicorn>=0.30.0
Requires-Dist: colorlog>=6.10.1
Requires-Dist: pydantic>=2.12.4
Requires-Dist: motor>=3.7.1
Requires-Dist: psycopg>=3.2.12
Requires-Dist: aiomysql>=0.3.2
Requires-Dist: aiohttp>=3.13.2
Requires-Dist: aiosmtplib>=3.0.1
Requires-Dist: aiofiles>=23.2.1
Requires-Dist: email-validator>=2.1.0
Requires-Dist: requests>=2.32.0
Requires-Dist: httpx>=0.28.1
Requires-Dist: passlib[bcrypt]>=1.7.4
Requires-Dist: python-jose[cryptography]>=3.5.0
Dynamic: license-file
